Metadata-Version: 2.1
Name: multicam
Version: 1.0.4
Summary: Syncronous reading from multiple webcams
Home-page: UNKNOWN
Author: Søren Rasmussen
Author-email: soren.rasmussen@alexandra.dk
License: UNKNOWN
Platform: UNKNOWN
Classifier: Programming Language :: Python :: 3
Classifier: License :: OSI Approved :: MIT License
Classifier: Operating System :: POSIX :: Linux
Requires-Python: >=3.6
